{
  "name": "Luke Pratt",
  "age": 46,
  "address": {
    "street": "Kolwiv Glen",
    "city": "Nouzuwu",
    "state": "MD",
    "zip": "52741"
  },
  "contact": {
    "phone": "(410) 505-3055",
    "servicePhone": "800138786"
  },
  "birthday": "2006-11-11T12:41:35.353Z",
  "ip": "83.92.145.117",
  "foo": "bar",
  "profile": {
    "about": "Siawrog em ini usurapas ogiosja femeweb ric ropazefi mut solagit etecet podet foh varuep. Hice ja nik tuuweuw hoj zof fumowsa epsu gibi lapi lih ru icavidlug wemguzwu subtuw wi pugkil hajlaj. Cotefun tazer te tug lot efimu betiwhe dusobud ke vebzuwuf nid hopdodos miklum tumgotdaj ticafe panfi.",
    "bio": "Dabo ji dofic ujuegaino kif baviva purcupe lora moni mud pusti huronavi fowje. Zuhaneb simogzo oclos ocoila sucaci poorogov hupezu haculcab samaw wi omdus wotcika nohcu iv. Evako dowzed lil hihajah lusbevuw lononi pekavob tis med kizjosib curjof sopo. Os me workavar pugbit up lir eza dojgugej umu kodoruv gevi venutpe hozavsu odiufdam lu. Gema gezfatu gedpisbi luclip cehoaci hego fov dozodoh wagetti baju mocu sure newdag. Goawa nu deek egzo iczi milinec sawtahdu pedrupen uhu sijihme wo feg vipewhi renaboah remtomub irane ahhej jaud."
  },
  "apiKey": "98f47f2404124d54f690f9ef7c56b1025c02060e0bf8759defc0ab1760995141",
  "currency": {
    "code": "SZL",
    "name": "Swaziland Lilangeni"
  }
}