{
  "name": "Kyle Moss",
  "age": 55,
  "address": {
    "street": "Sucun Point",
    "city": "Zimodaf",
    "state": "AZ",
    "zip": "47719"
  },
  "contact": {
    "phone": "(556) 936-6172",
    "servicePhone": "800223586"
  },
  "birthday": "1984-09-17T03:17:07.232Z",
  "ip": "125.140.53.106",
  "foo": "bar",
  "profile": {
    "about": "Tuhtog sapekwe opkade kubpudjov to iwcuz adajuvec zapru di najed jel lezhel fate siksa tuk zi. Obibizhan pugav zomci hesu pok do owcemval kosal fub zo jaf lapo ge isozowcit mo igibi. Kopkejdo ne cuglobod gadpaf fero me fuko daseev kuwtuega oducu ilo kehzif tawi ni mahbo. Adfaw utovi acoune ur ze hid je govutfe ar kahuw gatoz jogovu. Bo fiahi vebni luvgozep sabbaso agumuroz miwo ahoniffo lu wajguhed osos wutijo uledo gesna povez daavegu nat wehvo.",
    "bio": "Pejlov hu pizebi nutra oh was tomeza ciboro baujtow jihus vic saparopob relve fumgiz epu ogduci. Ebku hecduhar up zuno cisizci lu unijur uda kig it zorjanvam kunopid fozuvi bol luser. Vahomju fevufa vu kan erec ele lanajozo nuju nirde pemjo sac kubal ozonegpo soupoewe wuom foguhuze edocu fihvutib. Zephob nakza camja mu fi puhnahko nasiji to gilaovu vu poaldo dir ahnigca."
  },
  "apiKey": "e77ee633cd672de8a185066cbcd0d1cbf40b8a45d77c6cc1ebc1f695f9e3a55e",
  "currency": {
    "code": "MYR",
    "name": "Malaysia Ringgit"
  }
}